MANIFEST.in
README.md
setup.cfg
setup.py
reswmsecanalyzer/__init__.py
reswmsecanalyzer/reswmsecanalyzer.py
reswmsecanalyzer.egg-info/PKG-INFO
reswmsecanalyzer.egg-info/SOURCES.txt
reswmsecanalyzer.egg-info/dependency_links.txt
reswmsecanalyzer.egg-info/entry_points.txt
reswmsecanalyzer.egg-info/requires.txt
reswmsecanalyzer.egg-info/top_level.txt
reswmsecanalyzer/examples/multiple-rules/graph_to_cmd.png
reswmsecanalyzer/examples/multiple-rules/policy_example.png
reswmsecanalyzer/examples/multiple-rules/sec_globauth.xml
reswmsecanalyzer/examples/multiple-rules/sec_globauth_prettyprint.xml
reswmsecanalyzer/examples/multiple-rules-with-workspace-restriction/sec_globauth.xml
reswmsecanalyzer/examples/multiple-rules-with-workspace-restriction/sec_globauth_prettyprint.xml
reswmsecanalyzer/examples/multiple-rules-with-workspace-restriction/workspaces.xml
reswmsecanalyzer/examples/multiple-rules-with-workspace-restriction/workspaces_prettyprint.xml
reswmsecanalyzer/examples/one-rule/graph_to_cmd.png
reswmsecanalyzer/examples/one-rule/sec_globauth.xml
reswmsecanalyzer/examples/one-rule/sec_globauth_prettyprint.xml